{"Exif":{"Lat":53.30943333333333,"Long":-112.9959638888889,"Date":"2024-05-24T14:31:01-06:00","Tags":{"ApertureValue":1.6637544366004915,"BrightnessValue":6.384020413045212,"ComponentsConfiguration":"","CustomRendered|int":"8","DateTimeDigitized|time.Time":"2024-05-24T14:31:01-06:00","DateTimeOriginal|time.Time":"2024-05-24T14:31:01-06:00","DateTime|time.Time":"2024-05-24T14:31:01-06:00","ExposureTime|*big.Rat":"1/394","FNumber":1.7799999713880652,"FocalLength":6.764999865652793,"FocalLengthIn35mmFilm|int":"48","ISOSpeedRatings|int":"64","LensMake":"Apple","LensModel":"iPhone 15 Pro back triple camera 6.765mm f/1.78","Make":"Apple","Model":"iPhone 15 Pro","Orientation|int":"1","PixelXDimension|int":"1125","PixelYDimension|int":"1500","SceneCaptureType|int":"0","SceneType":"","ShutterSpeedValue":8.623798539023452,"Software":"Photomator 3.3.13","SubSecTime":"481","SubSecTimeDigitized":"481","SubSecTimeOriginal":"481","SubjectArea":[2117,1457,371,374]}}}
