{"Exif":{"Lat":53.340722222222226,"Long":-112.986275,"Date":"2024-05-29T15:59:23-06:00","Tags":{"ApertureValue":1.6637544366004915,"BrightnessValue":9.446073834086452,"DateTimeDigitized|time.Time":"2024-05-29T15:59:23-06:00","DateTimeOriginal|time.Time":"2024-05-29T15:59:23-06:00","DateTime|time.Time":"2024-05-29T15:59:23-06:00","ExposureTime|*big.Rat":"1/3425","FNumber":1.7799999713880652,"FocalLength":6.764999865652793,"FocalLengthIn35mmFilm|int":"48","ISOSpeedRatings|int":"64","LensMake":"Apple","LensModel":"iPhone 15 Pro back triple camera 6.765mm f/1.78","Make":"Apple","Model":"iPhone 15 Pro","Orientation|int":"1","PixelXDimension|int":"1125","PixelYDimension|int":"1500","SceneType":"","ShutterSpeedValue":11.741744010360458,"Software":"Photomator 3.3.14","SubSecTimeDigitized":"888","SubSecTimeOriginal":"888","SubjectArea":[2017,1508,1161,665]}}}
